{ "SettingsExtensionsMetadata": { "AccountPageDisplayName": "آپ کا Microsoft اکاﺅنٹ", "AccountPageDescription": "سبسکرپشنز، انعامات وغیرہ", "AccountPageSearchDataDescription1": "اپنے Microsoft اکاؤنٹ کو مینیج کریں", "AccountPageSearchDataKeywords1": "microsoft اکاؤنٹ؛اکاؤنٹ", "AccountPageSearchDataDescription2": "اپنی سبسکرپشنز کو مینیج کریں", "AccountPageSearchDataKeywords2": "سبسکرپشن؛سبسکرپشنز؛microsoft 365;microsoft 365 کی سبسکرپشن؛سبسکرپشن کو مینیج کریں؛سبسکرپشنز کو مینیج کریں", "AccountPageSearchDataDescription3": "Microsoft Rewards", "AccountPageSearchDataKeywords3": "انعامات؛microsoft rewards", "AccountPageSearchDataDescription4": "ادائیگی اور بلنگ", "AccountPageSearchDataKeywords4": "ادائیگی؛ادائیگیاں؛ادائیگی کے اختیارات؛کریڈٹ کارڈ؛بلنگ؛آرڈر؛آرڈرز" }, "States": { "Default": { "SubscriptionsSectionTitle": "آپ کی سبسکرپشنز", "SubscriptionsSectionAccessibilityGroup": "آپ کی سبسکرپشنز، گروپ", "SubscriptionName": "loc پائپ لائن کو ٹیسٹ کرنے کے لئے اس سٹرنگ کو تبدیل کیا جا رہا ہے۔ Microsoft 365", "SubscriptionDescription": "Premium Office کی ایپس، OneDrive کی کلاؤڈ اسٹوریج، اور مزید بہت کچھ", "SubscriptionState": "", "SubscriptionBody": "اپنے خاندان کے پانچ تک افراد کے ساتھ شیئر کرنے کے لئے ایک با سہولت سبسکرپشن۔ اس میں پریمیم کارآمد ایپس اور {{totalMemory}} تک کلاؤڈ اسٹوریج بھی شامل ہے – {{perPersonMemory}} فی فرد – اور آپ کے تمام آلات کے لئے اعلی درجے کی سیکورٹی بھی۔", "SubscriptionCtaText": "آغاز کریں", "SubscriptionCtaText2": "مزید جانیں", "PriceTermYear": "سال", "CardBodyHeaderBilling": "مکرر بلنگ", "CardBodyCTABilling": "بندوبست کریں", "CardBodyHeaderPI": "طریقہ ادائیگی", "CardBodyCTAPI": "تبديل کريں", "ShareHeader": "شیئر کریں", "ShareHeaderSharing": "آپ ان کے ساتھ شیئر کررہے ہیں", "ShareBody": "پانچ افراد تک", "ShareCta": "اشتراک کرنا شروع کریں", "ShareBeneficiaryHeader": "اسے یہ شیئر اور مینیج کرتے ہیں", "ShareCtaSharing": "شیئرنگ کو مینیج کریں", "BillingTitle": "اکاؤنٹ اور بلنگ کے متعلق مدد", "BillingTitleA": "اکاؤنٹ اور بلنگ کے متعلق مدد", "BillingTitleB": "اکاؤنٹ کے متعلق مدد", "BillingSubtitle": "سبسکرپشنز، ادائیگیوں اور بلنگ کے لیے معاونت حاصل کریں", "SubscriptionBillingCta": "تفصیلات دیکھیں", "SubscriptionBillingHeader": "مکرر بلنگ", "SubscriptionPaymentHeader": "طریقہ ادائیگی", "SubscriptionPaymentCta": "تبديل کريں", "ManageHeader": "اگلی کٹوتی {{date}} ({{price}} جمع قابل اطلاق ٹیکسز)", "ManageCta": "مینیج کریں", "OneDriveIcon": "OneDrive شبیہ", "OneDriveBody": "OneDrive اسٹوریج کے {{storageTotal}} میں سے {{storageUsed}} استعمال ہوا", "OneDriveBodyError": "آپ کی سبسکرپشن میں {{storageTotal}} کا OneDrive کلاؤڈ اسٹوریج شامل ہے", "OneDriveCta": "OneDrive کھولیں", "BenefitsBody": "اپنی {{productName}} سبسکرپشن کے تمام فوائد دیکھیں", "BenefitsCta": "فوائد دیکھیں", "RelatedLinkSectionAccessibilityGroup": "متعلقہ، گروپ", "RelatedLinkSectionTitle": "متعلقہ", "FooterLink1": "بلنگ کے بارے میں مدد حاصل کریں", "AllSubscriptionsTitle": "تمام سبسکرپشنز", "RewardsTitle": "انعامات", "RewardsSubtitle": "اپنی پسندیدہ خدمات استعمال کرکے پوائنٹس کمائیں اور ریڈیم کریں، اور مزید بہت کچھ", "PaymentTitle": "ادائیگی کے اختیارات", "PaymentSubtitle": "اپنے Microsoft اکاؤنٹ کے ساتھ آپ خریداریوں کے لیے کیسے ادائیگی کرتے ہیں بندوبست کریں", "HistoryTitle": "آرڈر کی سرگزشت", "HistorySubtitle": "اپنے Microsoft اکاؤنٹ کے ساتھ کی گئی حالیہ خریداریاں دیکھیں", "SubscriptionsTitle": "رکنیتیں", "SubscriptionsSubtitle": "Microsoft کی سروسز اور سبسکرپشنز کو مینیج کریں", "UpsellHeader": "{{productName}} فیملی", "UpsellDescription": "ایک با سہولت سبسکرپشن جو پانچ تک دیگر افراد کے ساتھ شیئر کی جا سکتی ہے۔ اس میں پریمیم Office ایپس بھی شامل ہیں اور {{totalBytes}} کی کلاؤڈ اسٹوریج بھی ({{bytesPerPerson}} فی شخص) ۔", "UpsellCta": "آغاز کریں", "InfoCta": "مزید جانیے", "SubscriptionPrice": "{{قیمت}} / {{دورانیہ}}" }, "OEMOffer": {}, "TrialUpsell": { "UpsellHeader": "{{productName}} کو مفت میں ازمائیں", "UpsellCta": "مفت میں آزمائیں" }, "AcquisitionUpsell": {}, "ActivePersonal": { "ShareHeader": "اپنی سبسکرپشن کو دیگر پانچ تک کے ساتھ شیئر کریں", "ShareCta": "اپ گریڈ" }, "ActiveFamily": {}, "InDunning": { "ManageHeader": "{{totalPastDue}} پچھلا واجب الادا", "ManageCta": "ابھی ادائیگی کریں", "SubscriptionBillingCta": "مزید جانیے", "SubscriptionPrice": "{{totalPastDue}} پچھلا واجب الادا", "SubscriptionState": "میعاد جلد ہی ختم ہونے والی ہے" }, "RecurringOffPersonal": { "ShareHeader": "اپنی سبسکرپشن کو پانچ تک دیگر کے ساتھ شیئر کریں", "ShareCta": "اپ گریڈ کریں", "ManageHeader": "آخری بار {{price}} کٹوتی {{date}} کو کی گئی", "SubscriptionBillingHeader": "معیاد اس تاریخ کو ختم ہوگی", "SubscriptionBillingCta": "مکرر بلنگ کو سیٹ اپ کریں" }, "RecurringOffPersonalExpiringSoon": { "ShareHeader": "اپنی سبسکرپشن کو پانچ تک دیگر افراد کے ساتھ شیئر کریں", "ShareCta": "درجہ فزوں کریں", "ManageHeader": "آخری بار {{price}} کٹوتی {{date}} کو کی گئی", "SubscriptionBillingHeader": "معیاد ختم ہوتی ہے", "SubscriptionBillingCta": "مکرر بلنگ کو سیٹ اپ کریں", "SubscriptionState": "میعاد جلد ہی ختم ہونے والی ہے" }, "RecurringOffFamily": { "ManageHeader": "آخری بار {{price}} کٹوتی {{date}} کو کی گئی", "SubscriptionBillingHeader": "پر ختم ہوتا ہے", "SubscriptionBillingCta": "مکرر بلنگ کو سیٹ اپ کریں" }, "RecurringOffFamilyExpiringSoon": { "ManageHeader": "آخری بار {{price}} کٹوتی {{date}} کو کی گئی", "SubscriptionBillingHeader": "معیاد ختم ہوتی ہے", "SubscriptionBillingCta": "مکرر بلنگ کو سیٹ اپ کریں", "SubscriptionState": "میعاد جلد ہی ختم ہونے والی ہے" }, "RedeemExpired": { "SubscriptionBillingHeader": "میعاد اس تاریخ کو ختم ہو گئی", "SubscriptionBillingCta": "دوبارہ سبسکرائب کریں" }, "RedeemFamily": { "SubscriptionBillingHeader": "معیاد اس تاریخ کو ختم ہوگی", "SubscriptionBillingCta": "مکرر بلنگ کو سیٹ اپ کریں" }, "RedeemFamilyExpiringSoon": { "SubscriptionBillingHeader": "معیاد ختم ہوتی ہے", "SubscriptionBillingCta": "مکرر بلنگ کو سیٹ اپ کریں", "SubscriptionState": "میعاد جلد ہی ختم ہونے والی ہے" }, "RedeemPersonal": { "ShareHeader": "اپنی سبسکرپشن کو پانچ تک دیگر افراد کے ساتھ شیئر کریں", "ShareCta": "اپ گریڈ کریں", "SubscriptionBillingHeader": "معیاد اس تاریخ کو ختم ہوگی", "SubscriptionBillingCta": "مکرر بلنگ کو سیٹ اپ کریں" }, "RedeemPersonalExpiringSoon": { "ShareHeader": "اپنی سبسکرپشن کو پانچ تک دیگر افراد کے ساتھ شیئر کریں", "ShareCta": "درجہ فزوں کریں", "SubscriptionBillingHeader": "معیاد ختم ہوتی ہے", "SubscriptionBillingCta": "مکرر بلنگ کو سیٹ اپ کریں", "SubscriptionState": "میعاد جلد ہی ختم ہونے والی ہے" }, "ExpiredPI": {}, "ExpiringPI": { "SubscriptionState": "میعاد جلد ہی ختم ہونے والی ہے" }, "Expired": { "ManageHeader": "آخری بار {{price}} کٹوتی {{date}} کو کی گئی", "SubscriptionBillingHeader": "مدت اس تاریخ کو ختم ہو گئی", "SubscriptionBillingCta": "دوبارہ سبسکرائب کریں" }, "PartnerManagedRecurringOn": { "SubscriptionBillingHeader": "مکرر بلنگ آن ہے", "SubscriptionPrice": "{{companyName}} سے خریدا گیا", "SubscriptionBillingCta": "بندوبست کریں" }, "PartnerManagedRecurringOff": { "SubscriptionBillingHeader": "مکرر بلنگ آف ہے", "SubscriptionPrice": "{{companyName}} سے خریدا گیا", "SubscriptionBillingCta": "بندوبست کریں" }, "PartnerManagedExpired": { "SubscriptionBillingHeader": "مدت ختم ہو گئی", "SubscriptionPrice": "{{companyName}} سے خریدا گیا", "SubscriptionBillingCta": "دوبارہ سبسکرائب کریں" }, "Beneficiary": {}, "Unavailable": {}, "StaleData": {}, "OneDriveUnavailable": {}, "Russia": {}, "SubRegionNotDeviceRegion": {} } }
